netspeedo/__init__.py
netspeedo/cli.py
netspeedo-0.1.0.dist-info/METADATA
netspeedo-0.1.0.dist-info/WHEEL
netspeedo-0.1.0.dist-info/entry_points.txt
netspeedo-0.1.0.dist-info/licenses/LICENSE
netspeedo-0.1.0.dist-info/RECORD
