Metadata-Version: 2.4
Name: netspeedo
Version: 0.1.0
Summary: A feature-rich, real-time network speed and performance monitor for your terminal.
Project-URL: Homepage, https://github.com/rajuX75/netspeedo
Project-URL: Bug Tracker, https://github.com/rajuX75/netspeedo/issues
Author-email: Raju <your-email@example.com>
License: MIT License
License-File: LICENSE
Keywords: cli,monitor,network,rich,speed,terminal
Classifier: Development Status :: 4 - Beta
Classifier: Intended Audience :: Developers
Classifier: Intended Audience :: System Administrators
Classifier: License :: OSI Approved :: MIT License
Classifier: Operating System :: OS Independent
Classifier: Programming Language :: Python :: 3
Classifier: Programming Language :: Python :: 3.8
Classifier: Programming Language :: Python :: 3.9
Classifier: Programming Language :: Python :: 3.10
Classifier: Programming Language :: Python :: 3.11
Classifier: Topic :: System :: Monitoring
Classifier: Topic :: Terminals
Requires-Python: >=3.8
Requires-Dist: psutil
Requires-Dist: requests
Requires-Dist: rich
